EpsilonGreedy/__init__.py
EpsilonGreedy/main.py
epsilongreedy-0.1.1.dist-info/METADATA
epsilongreedy-0.1.1.dist-info/WHEEL
epsilongreedy-0.1.1.dist-info/entry_points.txt
epsilongreedy-0.1.1.dist-info/top_level.txt
epsilongreedy-0.1.1.dist-info/RECORD
