Metadata-Version: 2.4
Name: EpsilonGreedy
Version: 0.1.1
Summary: A simple Epsilon-Greedy multi-armed bandit implementation
Home-page: https://github.com/priyanshi-furiya/epsilon-greedy
Author: Priyanshi Furiya
Author-email: furiyapriyanshi@gmail.com
Classifier: Programming Language :: Python :: 3
Classifier: License :: OSI Approved :: MIT License
Classifier: Operating System :: OS Independent
Classifier: Intended Audience :: Science/Research
Classifier: Topic :: Scientific/Engineering :: Artificial Intelligence
Requires-Python: >=3.7
Dynamic: author
Dynamic: author-email
Dynamic: classifier
Dynamic: description
Dynamic: description-content-type
Dynamic: home-page
Dynamic: requires-python
Dynamic: summary
